cedarscript_integration_aider/__init__.py
cedarscript_integration_aider/_version.py
cedarscript_integration_aider/cedarscript/README.md
cedarscript_integration_aider/cedarscript/edit_format_training.txt
cedarscript_integration_aider/cedarscript/example_messages.cedarml
cedarscript_integration_aider/cedarscript/final_remarks.txt
cedarscript_integration_aider/cedarscript/main_system.txt
cedarscript_integration_aider/cedarscript/no_shell_cmd_prompt.txt
cedarscript_integration_aider/cedarscript/shell_cmd_prompt.txt
cedarscript_integration_aider/cedarscript/shell_cmd_reminder.txt
cedarscript_integration_aider/cedarscript/system_reminder.txt
cedarscript_integration_aider/examples/detailed.prompt
cedarscript_integration_aider/examples/friendly.prompt
cedarscript_integration_aider/examples/minimal.prompt
cedarscript_integration_aider/examples/technical.prompt
cedarscript_integration_aider-1.4.0.dist-info/LICENSE
cedarscript_integration_aider-1.4.0.dist-info/METADATA
cedarscript_integration_aider-1.4.0.dist-info/WHEEL
cedarscript_integration_aider-1.4.0.dist-info/top_level.txt
cedarscript_integration_aider-1.4.0.dist-info/RECORD
