Metadata-Version: 2.1
Name: cedarscript-integration-aider
Version: 1.4.0
Summary: Allows `Aider` to use CEDARScript as an edit format
Author-email: Elifarley <cedarscript@orgecc.com>
License: Apache-2.0
Project-URL: Homepage, https://github.com/CEDARScript/cedarscript-integration-aider
Project-URL: Documentation, https://github.com/CEDARScript/cedarscript-integration-aider#readme
Project-URL: Repository, https://github.com/CEDARScript/cedarscript-integration-aider.git
Project-URL: Bug Tracker, https://github.com/CEDARScript/cedarscript-integration-aider/issues
Keywords: cedarscript,code-editing,refactoring,code-analysis,sql-like,ai-assisted-development
Classifier: Development Status :: 3 - Alpha
Classifier: Programming Language :: Python :: 3
Classifier: Programming Language :: Python :: 3.12
Classifier: License :: OSI Approved :: Apache Software License
Classifier: Operating System :: OS Independent
Classifier: Intended Audience :: Developers
Classifier: Topic :: Software Development :: Libraries :: Python Modules
Classifier: Topic :: Text Processing :: Linguistic
Classifier: Topic :: Software Development :: Code Generators
Classifier: Topic :: Software Development :: Compilers
Requires-Python: >=3.11
License-File: LICENSE
Provides-Extra: dev
Requires-Dist: pytest>=7.0; extra == "dev"
Requires-Dist: black>=22.0; extra == "dev"
Requires-Dist: isort>=5.0; extra == "dev"
Requires-Dist: flake8>=4.0; extra == "dev"
Requires-Dist: mypy>=0.900; extra == "dev"
Requires-Dist: coverage>=6.0; extra == "dev"
Requires-Dist: tox>=3.24; extra == "dev"
